platon_hash/__init__.py
platon_hash/abc.py
platon_hash/auto.py
platon_hash/main.py
platon_hash/py.typed
platon_hash/utils.py
platon_hash/backends/__init__.py
platon_hash/backends/auto.py
platon_hash/backends/pycryptodome.py
platon_hash/backends/pysha3.py
platon_hash/fnv/__init__.py
platon_hash/fnv/fvn.py
platon_hash-1.2.1.dist-info/LICENSE
platon_hash-1.2.1.dist-info/METADATA
platon_hash-1.2.1.dist-info/WHEEL
platon_hash-1.2.1.dist-info/top_level.txt
platon_hash-1.2.1.dist-info/RECORD
